S3MPython/__init__.py
S3MPython/dm.py
S3MPython/errors.py
S3MPython/ev.py
S3MPython/meta.py
S3MPython/ontology.py
S3MPython/project.py
S3MPython/settings.py
S3MPython/struct.py
S3MPython/utils.py
S3MPython/xdt.py
S3MPython-3.1.0.23.data/data/S3MPython/conf/S3MPython.conf
S3MPython-3.1.0.23.data/data/S3MPython/conf/acs.txt
S3MPython-3.1.0.23.data/data/S3MPython/s3model/dm-description.xsl
S3MPython-3.1.0.23.data/data/S3MPython/s3model/s3model.owl
S3MPython-3.1.0.23.data/data/S3MPython/s3model/s3model_3_1_0.rdf
S3MPython-3.1.0.23.data/data/S3MPython/s3model/s3model_3_1_0.xsd
S3MPython-3.1.0.23.data/data/S3MPython/s3model/s3model_3_1_0.xsl
S3MPython-3.1.0.23.dist-info/LICENSE
S3MPython-3.1.0.23.dist-info/METADATA
S3MPython-3.1.0.23.dist-info/WHEEL
S3MPython-3.1.0.23.dist-info/top_level.txt
S3MPython-3.1.0.23.dist-info/RECORD
